{"converted":1,"sec_color_id":"#e2b900","footer_text_id":"<p style=\"text-align: center\">This Demo Site is completely made with Optimizer WordPress Theme<\/p>","copyright_txt_color":"#777777","copyright_bg_color":"#262626","copyright_center":1,"footmenu_id":"","topmenu_switch":1,"topbar_bg_color":"#f2f2f2","topbar_color_id":"#666666","logo_image_id":{"url":"http:\/\/optimizer.layerthemes.com\/demo9\/wp-content\/uploads\/2015\/04\/demo9_logo.png"},"menutxt_color_id":"#878787","menutxt_color_hover":"#3d3d3d","menutxt_color_active":"#edd436","head_transparent":"","head_color_id":"#ffffff","static_image_id":{"url":"http:\/\/optimizer.layerthemes.com\/demo9\/wp-content\/uploads\/2015\/04\/entrepreneur-593358_slide.jpg"},"static_img_text_id":"<p><strong><span style=\"font-size: 60px\">IMPROVE YOUR<\/span><\/strong><br \/><strong><span style=\"font-size: 60px\"> BUSINESS<\/span><\/strong><\/p><p><strong>Analyze your business Data with ease!<\/strong><\/p>","static_cta1_text":"GET STARTED","static_cta1_txt_style":"flat","static_cta1_bg_color":"#f2db32","static_cta2_text":"LEARN MORE","static_cta2_bg_color":"#ffffff","static_cta2_txt_color":"#777777","static_textbox_bottom":"4","slider_content_align":"left","social_show_color":1,"social_bookmark_pos":"topbar","facebook_field_id":"http:\/\/facebook.com\/layerthemes\/","twitter_field_id":"http:\/\/twitter.com\/layer_themes","gplus_field_id":"https:\/\/plus.google.com\/u\/0\/103483167150562533630\/about","tophone_id":"(212) 504-4115"}