{"converted":1,"logo_color_id":"#1c1c1c","logo_position":"logo_middle","menutxt_color_id":"#606060","head_transparent":"","menu_size_id":"12px","logo_font_id":{"font-size":"36px","font-family":"Montserrat"},"hide_tagline":1,"menutxt_color_hover":"#8e8e8e","menutxt_color_active":"#0a0000","static_image_id":{"url":""},"static_gallery":"","slider_type_id":"nivo","nivo_accord_slider":"55,56,57,58","ptitle_font_id":{"font-family":"Montserrat"},"content_font_id":{"font-family":"Crimson Text"},"footer_color_id":"#0c0c0c","copyright_center":1,"footmenu_id":"","copyright_bg_color":"#0c0c0c","social_button_style":"hexagon","social_bookmark_size":"normal","facebook_field_id":"https:\/\/www.facebook.com\/optimizerwp\/","twitter_field_id":"https:\/\/www.twitter.com\/optimizerwp\/","gplus_field_id":"https:\/\/plus.google.com\/+Layerthemes\/posts","logo_image_id":{"url":"http:\/\/presets.layerthemes.netdna-cdn.com\/demo17\/logo.png"},"head_color_id":"#ffffff","portfolio_single_layout":"3","sec_color_id":"#0a0000","slider_txt_hide":1,"page_header_color":"#0a0a0a","page_header_txtcolor":"#d1d1d1","portfolio_layout":"2","portfolio_hover_layout":"5"}